hui2/__init__.py
hui2/core.py
hui2-0.3.1.dist-info/METADATA
hui2-0.3.1.dist-info/WHEEL
hui2-0.3.1.dist-info/top_level.txt
hui2-0.3.1.dist-info/RECORD
