Metadata-Version: 2.1
Name: hui2
Version: 0.3.1
Summary: Android automation library with OCR support based on uiautomator2
Home-page: https://github.com/h1code2/hui2
Author: h1code2
Author-email: h1code2@163.com
Keywords: android automation ocr uiautomator2 testing
Classifier: Development Status :: 4 - Beta
Classifier: Intended Audience :: Developers
Classifier: License :: OSI Approved :: MIT License
Classifier: Programming Language :: Python :: 3
Classifier: Programming Language :: Python :: 3.8
Classifier: Programming Language :: Python :: 3.9
Classifier: Programming Language :: Python :: 3.10
Classifier: Programming Language :: Python :: 3.11
Classifier: Topic :: Software Development :: Libraries :: Python Modules
Classifier: Topic :: Software Development :: Testing
Classifier: Topic :: Utilities
Requires-Python: >=3.8
Requires-Dist: uiautomator2 >=3.4.1
Requires-Dist: rapidocr-onnxruntime >=1.4.4
Requires-Dist: loguru >=0.7.3
Requires-Dist: opencv-python >=4.12.0.88
